Metadata-Version: 1.2
Name: seisample
Version: 1.0.1
Summary: to generate seismic samples
Home-page: http://homepage.hit.edu.cn/pages/siweiyu
Author: siwei
Author-email: siweiyu.hit@foxmail.com
Maintainer: siweiyu
Maintainer-email: siweiyu.hit@foxmail.com
License: BSD License
Platform: all
Classifier: Development Status :: 4 - Beta
Classifier: Operating System :: OS Independent
Classifier: Intended Audience :: Developers
Classifier: License :: OSI Approved :: BSD License
Classifier: Programming Language :: Python
Classifier: Programming Language :: Python :: Implementation
Classifier: Programming Language :: Python :: 2
Classifier: Programming Language :: Python :: 2.7
Classifier: Programming Language :: Python :: 3
Classifier: Programming Language :: Python :: 3.4
Classifier: Programming Language :: Python :: 3.5
Classifier: Programming Language :: Python :: 3.6
Classifier: Topic :: Software Development :: Libraries
